[
	{
		"key": "left",
		"time": 0.25832200050354
	},
	{
		"key": "up",
		"time": 0.461496591567993
	},
	{
		"key": "down",
		"time": 0.684988677501678
	},
	{
		"key": "right",
		"time": 0.888163268566132
	},
	{
		"key": "left",
		"time": 1.11165535449982
	},
	{
		"key": "up",
		"time": 1.451247215271
	},
	{
		"key": "down",
		"time": 1.65442180633545
	},
	{
		"key": "right",
		"time": 1.87791383266449
	},
	{
		"key": "left",
		"time": 2.08108854293823
	},
	{
		"key": "up",
		"time": 2.32780051231384
	},
	{
		"key": "down",
		"time": 2.64707493782043
	},
	{
		"key": "right",
		"time": 2.85024952888489
	},
	{
		"key": "left",
		"time": 3.07374143600464
	},
	{
		"key": "up",
		"time": 3.27691602706909
	},
	{
		"key": "down",
		"time": 3.50040817260742
	},
	{
		"key": "right",
		"time": 3.70358276367188
	},
	{
		"key": "left",
		"time": 3.90675735473633
	},
	{
		"key": "up",
		"time": 4.26666688919067
	},
	{
		"key": "down",
		"time": 4.46984148025513
	},
	{
		"key": "right",
		"time": 4.6933331489563
	},
	{
		"key": "left",
		"time": 5.03582763671875
	},
	{
		"key": "up",
		"time": 5.2390022277832
	},
	{
		"key": "down",
		"time": 5.46249437332153
	},
	{
		"key": "right",
		"time": 5.66566896438599
	},
	{
		"key": "left",
		"time": 5.88916110992432
	},
	{
		"key": "up",
		"time": 6.09233570098877
	},
	{
		"key": "down",
		"time": 6.3158278465271
	},
	{
		"key": "right",
		"time": 6.65832185745239
	},
	{
		"key": "left",
		"time": 6.86149644851685
	},
	{
		"key": "up",
		"time": 7.08498859405518
	},
	{
		"key": "down",
		"time": 7.28816318511963
	},
	{
		"key": "right",
		"time": 7.51165533065796
	},
	{
		"key": "left",
		"time": 7.89478445053101
	},
	{
		"key": "up",
		"time": 8.23727893829346
	},
	{
		"key": "down",
		"time": 8.43755054473877
	},
	{
		"key": "right",
		"time": 8.66394519805908
	},
	{
		"key": "left",
		"time": 8.86421775817871
	},
	{
		"key": "up",
		"time": 9.09061241149902
	},
	{
		"key": "down",
		"time": 9.29088401794434
	},
	{
		"key": "right",
		"time": 9.51727867126465
	},
	{
		"key": "left",
		"time": 9.85687065124512
	},
	{
		"key": "up",
		"time": 10.0600452423096
	},
	{
		"key": "down",
		"time": 10.2835378646851
	},
	{
		"key": "right",
		"time": 10.6666669845581
	},
	{
		"key": "left",
		"time": 10.8698415756226
	},
	{
		"key": "up",
		"time": 11.0933332443237
	},
	{
		"key": "down",
		"time": 11.2965078353882
	},
	{
		"key": "right",
		"time": 11.4996824264526
	},
	{
		"key": "left",
		"time": 11.862494468689
	},
	{
		"key": "up",
		"time": 12.0656690597534
	},
	{
		"key": "down",
		"time": 12.2891607284546
	},
	{
		"key": "right",
		"time": 12.6722898483276
	},
	{
		"key": "left",
		"time": 12.8754644393921
	}
]
